steptools/py.typed
steptools/step.abi3.so
steptools/step.pyi
steptools-20.5.dist-info/LICENSE
steptools-20.5.dist-info/METADATA
steptools-20.5.dist-info/WHEEL
steptools-20.5.dist-info/top_level.txt
steptools-20.5.dist-info/RECORD
