Metadata-Version: 2.1
Name: steptools
Version: 20.5
Summary: STEP and STEP-NC (ISO 10303) native extension for large CAD/CAM/CAE models and machine tool interfaces.
Author-email: "STEP Tools, Inc" <support@steptools.com>
License: 
Project-URL: homepage, https://steptools.com
Project-URL: documentation, https://www.steptools.com/docs/stpython/
Project-URL: changelog, https://www.steptools.com/docs/stpython/news.html
Keywords: STEP,STEP-NC,ISO 10303,AP238,AP242,CAD,CAM,CNC,machine tool,robot,robots,manufacturing,digital twin,digital thread
Classifier: Intended Audience :: Manufacturing
Classifier: Intended Audience :: Information Technology
Classifier: License :: Other/Proprietary License
Classifier: Topic :: Database
Classifier: Topic :: File Formats
Classifier: Topic :: Multimedia :: Graphics :: 3D Modeling
Classifier: Topic :: Scientific/Engineering
Requires-Python: >=3.7
License-File: LICENSE
